disproces/__init__.py
disproces/main.py
disproces/timer.py
disproces-0.1.0.dist-info/LICENCE.txt
disproces-0.1.0.dist-info/METADATA
disproces-0.1.0.dist-info/WHEEL
disproces-0.1.0.dist-info/entry_points.txt
disproces-0.1.0.dist-info/top_level.txt
disproces-0.1.0.dist-info/RECORD
